PyFixedReps_andnp-4.1.2.dist-info/METADATA
PyFixedReps_andnp-4.1.2.dist-info/WHEEL
PyFixedReps/TileCoder.py
PyFixedReps/__init__.py
PyFixedReps/RBF.py
PyFixedReps/py.typed
PyFixedReps/_jit.py
PyFixedReps/BaseRepresentation.py
PyFixedReps/rust.cpython-310-darwin.so
PyFixedReps_andnp-4.1.2.dist-info/RECORD
