Metadata-Version: 2.3
Name: PyFixedReps-andnp
Version: 4.1.2
Classifier: Programming Language :: Rust
Classifier: Programming Language :: Python :: Implementation :: CPython
Classifier: Programming Language :: Python :: Implementation :: PyPy
Requires-Dist: numpy >=1.23, <3.0
Requires-Dist: numba ~=0.56
Requires-Dist: pip ; extra == 'dev'
Requires-Dist: ruff ; extra == 'dev'
Requires-Dist: pyright ; extra == 'dev'
Requires-Dist: commitizen ; extra == 'dev'
Requires-Dist: pre-commit ; extra == 'dev'
Requires-Dist: pytest >=7.3, <9.0 ; extra == 'dev'
Requires-Dist: pytest-benchmark >=4, <6 ; extra == 'dev'
Requires-Dist: maturin >=1.4, <1.8 ; extra == 'dev'
Provides-Extra: dev
Summary: 
Author-email: Andy Patterson <andnpatterson@gmail.com>
License: MIT
Requires-Python: >=3.10, <3.13
